<?xml version="1.0" encoding="utf-8" ?>
<dwsync>
<file name="carbon.jpg" local="131807426349402851" remote="131846950800000000" testing="0" />
<file name="JLD_1.jpg" local="131846891013020363" remote="131846950800000000" testing="0" />
<file name="JLD_2.jpg" local="131846891489438530" remote="131846950800000000" testing="0" />
<file name="JLD_3.jpg" local="131846891856881983" remote="131846950800000000" testing="0" />
<file name="JLD_4.jpg" local="131846892200413066" remote="131846950800000000" testing="0" />
<file name="JLD_5.jpg" local="131846892417382695" remote="131846950800000000" testing="0" />
<file name="JLD_6.jpg" local="131846892763486897" remote="131846950800000000" testing="0" />
<file name="JLD_7.jpg" local="131846892927358555" remote="131846950800000000" testing="0" />
<file name="JLD_9.jpg" local="131846893724586045" remote="131846950800000000" testing="0" />
<file name="JLD_10.jpg" local="131846893908593845" remote="131846950800000000" testing="0" />
<file name="JLD_11.jpg" local="131846894164429502" remote="131846950800000000" testing="0" />
<file name="JLD_12.jpg" local="131846894274993757" remote="131846950800000000" testing="0" />
<file name="JLD_13.jpg" local="131846894447173878" remote="131846950800000000" testing="0" />
<file name="JLD_14.jpg" local="131846894642677666" remote="131846950800000000" testing="0" />
<file name="JLD_15.jpg" local="131846894804844374" remote="131846950800000000" testing="0" />
<file name="JLD_16.jpg" local="131846894931794794" remote="131846950800000000" testing="0" />
<file name="JLD_8.jpg" local="131846893510309215" remote="131846962200000000" testing="0" />
<file name="wot-logo1.png" local="131818423679347021" remote="131846976000000000" testing="0" />
</dwsync>